Metadata-Version: 2.4
Name: quantaxis_webserver-lance
Version: 2.0.0
Summary: QUANTAXIS WEBSERVER: WEBSERVER FOR QUANTAXIS
Home-page: https://github.com/yutiansut/quantaxis_webserver
Author: yutiansut
Author-email: yutiansut@qq.com
License: MIT
Keywords: quantaxis,quant,finance,Backtest,Framework
Classifier: License :: OSI Approved :: MIT License
Classifier: Programming Language :: Python
Classifier: Intended Audience :: Developers
Classifier: Operating System :: OS Independent
License-File: LICENSE
Requires-Dist: tornado>=6.1
Requires-Dist: qaenv
Requires-Dist: apscheduler
Requires-Dist: quantaxis>=1.7.0
Dynamic: author
Dynamic: author-email
Dynamic: classifier
Dynamic: description
Dynamic: home-page
Dynamic: keywords
Dynamic: license
Dynamic: license-file
Dynamic: requires-dist
Dynamic: summary
